{
  "type": "native",
  "devices": {
    "Pixel3W": {}
  },
  "repetitions": 1,
  "apps": [
    "com.android.chrome"
  ],
  "duration": 2000,
  "profilers": {
    "android": {
      "subject_aggregation": "default",
      "experiment_aggregation": "Scripts/aggregate_android.py",
      "sample_interval": 100,
      "data_points": [

      ]
    }
  },
  "scripts": {
          "interaction": [
      {
        "type": "monkeyadb",
        "path": "Scripts/monkey.txt"
      }
    ]
  },
  "time_between_run": 500
}